[{
  "name": "通山游记",
  "cover": "https://s1.ax1x.com/2022/10/02/xMGTjU.jpg",
  "description": "你走后天还是那么蓝",
  "photos": [
    "https://s1.ax1x.com/2022/10/02/xMGx9x.jpg",
    "https://s1.ax1x.com/2022/10/02/xMGTjU.jpg",
    "https://s1.ax1x.com/2022/10/02/xMGHuF.jpg",
    "https://s1.ax1x.com/2022/10/02/xMGbB4.jpg",
    "https://s1.ax1x.com/2022/10/02/xMGz36.jpg",
    "https://s1.ax1x.com/2022/10/02/xMGqHJ.jpg",
    "https://s1.ax1x.com/2022/10/02/xMGOE9.jpg",
    "https://s1.ax1x.com/2022/10/02/xMGXNR.jpg",
    "https://s1.ax1x.com/2022/10/02/xMGj41.jpg"
  ]
}, {
  "name": "军运会",
  "cover": "https://s1.ax1x.com/2022/10/02/xMdgxI.jpg",
  "description": "炎热的夏季总会发生一些有趣的事情，比如我和四年前的你",
  "photos": [
    "https://s1.ax1x.com/2022/10/02/xMdWsP.jpg",
    "https://s1.ax1x.com/2022/10/02/xMd4Z8.jpg",
    "https://s1.ax1x.com/2022/10/02/xMd5dS.jpg",
    "https://s1.ax1x.com/2022/10/02/xMdRMt.jpg",
    "https://s1.ax1x.com/2022/10/02/xMdgxI.jpg",
    "https://s1.ax1x.com/2022/10/02/xMdfqf.jpg",
    "https://s1.ax1x.com/2022/10/02/xMdTiQ.jpg",
    "https://s1.ax1x.com/2022/10/02/xMd7Gj.jpg",
    "https://s1.ax1x.com/2022/10/02/xMdIIg.jpg"
  ]
}, {
  "name": "北京参赛随记",
  "cover": "/images/theme/post-image.jpg",
  "description": "斑马斑马，你不要睡着啦，我只是个匆忙的旅人啊。",
  "photos": [
    "/images/theme/post-image.jpg"
    
  ]
}]